flipboard/__init__.py
flipboard/cli.py
flipboard-0.3.0.dist-info/METADATA
flipboard-0.3.0.dist-info/WHEEL
flipboard-0.3.0.dist-info/entry_points.txt
flipboard-0.3.0.dist-info/licenses/LICENSE
flipboard-0.3.0.dist-info/RECORD
